sbom2dot/__init__.py
sbom2dot/cli.py
sbom2dot/dotgenerator.py
sbom2dot/version.py
sbom2dot-0.3.2.dist-info/METADATA
sbom2dot-0.3.2.dist-info/WHEEL
sbom2dot-0.3.2.dist-info/entry_points.txt
sbom2dot-0.3.2.dist-info/top_level.txt
sbom2dot-0.3.2.dist-info/RECORD
